{
  "photo-1": 51,
  "photo-2": 40,
  "photo-3": 286,
  "photo-4": 144,
  "photo-5": 0,
  "photo-6": 31,
  "photo-7": 6,
  "photo-8": 5,
  "photo-9": 6,
  "photo-10": 5,
  "photo-11": 5,
  "photo-12": 22,
  "photo-13": 8,
  "photo-14": 9,
  "photo-15": 36,
  "photo-16": 4,
  "photo-17": 79,
  "photo-18": 138,
  "photo-19": 23,
  "photo-20": 28,
  "photo-21": 25,
  "photo-22": 11,
  "photo-23": 8,
  "photo-24": 30,
  "photo-25": 9,
  "photo-26": 24,
  "photo-27": 57,
  "photo-28": 17,
  "photo-29": 61,
  "photo-30": 5,
  "photo-31": 52,
  "photo-32": 66
}